woomodule/__init__.py
woomodule/__main__.py
woomodule/app/__init__.py
woomodule/app/app.py
woomodule-2.0.3.dist-info/LICENSE
woomodule-2.0.3.dist-info/METADATA
woomodule-2.0.3.dist-info/WHEEL
woomodule-2.0.3.dist-info/entry_points.txt
woomodule-2.0.3.dist-info/top_level.txt
woomodule-2.0.3.dist-info/RECORD
