Metadata-Version: 2.1
Name: woomodule
Version: 2.0.3
Summary: Package for practice
Home-page: UNKNOWN
Author: Dihtiar Vadym
License: UNKNOWN
Platform: UNKNOWN
Requires-Python: >=3.8
License-File: LICENSE
Requires-Dist: pytest (==7.2.0)
